redturtle.filesretriever-1.0.4-py3.10-nspkg.pth
redturtle/filesretriever/__init__.py
redturtle/filesretriever/configure.zcml
redturtle/filesretriever/testing.py
redturtle/filesretriever/browser/__init__.py
redturtle/filesretriever/browser/configure.zcml
redturtle/filesretriever/browser/filesretriever.pt
redturtle/filesretriever/browser/view.py
redturtle/filesretriever/browser/overrides/.gitkeep
redturtle/filesretriever/browser/static/react/logo_rer.gif
redturtle/filesretriever/browser/static/react/dist/prod/filesretriever.css
redturtle/filesretriever/browser/static/react/dist/prod/filesretriever.css.map
redturtle/filesretriever/browser/static/react/dist/prod/filesretriever.js
redturtle/filesretriever/browser/static/react/dist/prod/filesretriever.js.map
redturtle/filesretriever/browser/static/react/javascripts/ApiContext.js
redturtle/filesretriever/browser/static/react/javascripts/TranslationsContext.js
redturtle/filesretriever/browser/static/react/javascripts/filesretriever/App.js
redturtle/filesretriever/browser/static/react/javascripts/filesretriever/App.less
redturtle/filesretriever/browser/static/react/javascripts/filesretriever/index.js
redturtle/filesretriever/browser/static/react/javascripts/filesretriever/utils.js
redturtle/filesretriever/browser/static/react/javascripts/filesretriever/FilesListWrapper/index.jsx
redturtle/filesretriever/browser/static/react/javascripts/filesretriever/FilesListWrapper/index.less
redturtle/filesretriever/browser/static/react/javascripts/filesretriever/FilesRetrieverWrapper/index.jsx
redturtle/filesretriever/browser/static/react/javascripts/filesretriever/FilesRetrieverWrapper/index.less
redturtle/filesretriever/browser/static/react/javascripts/filesretriever/SearchForm/index.jsx
redturtle/filesretriever/browser/static/react/javascripts/filesretriever/SearchForm/index.less
redturtle/filesretriever/browser/static/react/javascripts/filesretriever/TitleRow/index.jsx
redturtle.filesretriever-1.0.4.dist-info/LICENSE.GPL
redturtle.filesretriever-1.0.4.dist-info/LICENSE.rst
redturtle.filesretriever-1.0.4.dist-info/METADATA
redturtle.filesretriever-1.0.4.dist-info/WHEEL
redturtle.filesretriever-1.0.4.dist-info/entry_points.txt
redturtle.filesretriever-1.0.4.dist-info/namespace_packages.txt
redturtle.filesretriever-1.0.4.dist-info/top_level.txt
redturtle.filesretriever-1.0.4.dist-info/RECORD
